{
  "id": "session-1773694792518",
  "status": "stopped",
  "startedAt": "2026-03-16T20:59:52.518Z",
  "stoppedAt": "2026-03-16T20:59:52.518Z",
  "chunks": [],
  "events": [
    {
      "type": "session_started",
      "detail": {
        "id": "session-1773694792518"
      },
      "timestamp": "2026-03-16T20:59:52.518Z"
    },
    {
      "type": "session_stopped",
      "detail": {},
      "timestamp": "2026-03-16T20:59:52.518Z"
    }
  ],
  "coachingState": "green",
  "coachingMessage": "",
  "escalationLevel": 0,
  "consecutiveWarnings": 0,
  "totalSpeakingSeconds": 0,
  "thresholds": {
    "greenMax": 45,
    "yellowMax": 90
  }
}